[{"userProfilePK":96200873,"calendarDate":"2021-05-31","deviceId":3366988290,"updateTimestamp":"2021-05-31T22:02:29.0","sport":"RUNNING","subSport":"GENERIC","vo2MaxValue":57.0,"fitnessAge":"20","fitnessAgeDescription":"3","analyzerMethod":5,"maxMet":16.378128051757812,"maxMetCategory":"GENERIC","calibratedData":1},{"userProfilePK":96200873,"calendarDate":"2021-06-02","deviceId":3366988290,"updateTimestamp":"2021-06-02T14:57:41.0","sport":"RUNNING","subSport":"GENERIC","vo2MaxValue":57.0,"fitnessAge":"20","fitnessAgeDescription":"3","analyzerMethod":5,"maxMet":16.417495727539062,"maxMetCategory":"GENERIC","calibratedData":1},{"userProfilePK":96200873,"calendarDate":"2021-06-02","deviceId":3366988290,"updateTimestamp":"2021-06-04T22:28:10.0","sport":"RUNNING","subSport":"GENERIC","vo2MaxValue":58.0,"fitnessAge":"20","fitnessAgeDescription":"3","analyzerMethod":5,"maxMet":16.5606689453125,"maxMetCategory":"GENERIC","calibratedData":1},{"userProfilePK":96200873,"calendarDate":"2021-06-02","deviceId":3366988290,"updateTimestamp":"2021-06-05T17:03:52.0","sport":"RUNNING","subSport":"GENERIC","vo2MaxValue":58.0,"fitnessAge":"20","fitnessAgeDescription":"3","analyzerMethod":5,"maxMet":16.553970336914062,"maxMetCategory":"GENERIC","calibratedData":1},{"userProfilePK":96200873,"calendarDate":"2021-06-07","deviceId":3366988290,"updateTimestamp":"2021-06-07T22:15:14.0","sport":"RUNNING","subSport":"GENERIC","vo2MaxValue":59.0,"fitnessAge":"20","fitnessAgeDescription":"3","analyzerMethod":5,"maxMet":16.77557373046875,"maxMetCategory":"GENERIC","calibratedData":1},{"userProfilePK":96200873,"calendarDate":"2021-06-07","deviceId":3366988290,"updateTimestamp":"2021-06-08T22:09:49.0","sport":"RUNNING","subSport":"GENERIC","vo2MaxValue":59.0,"fitnessAge":"20","fitnessAgeDescription":"3","analyzerMethod":5,"maxMet":16.902557373046875,"maxMetCategory":"GENERIC","calibratedData":1},{"userProfilePK":96200873,"calendarDate":"2021-06-07","deviceId":3366988290,"updateTimestamp":"2021-06-11T22:24:41.0","sport":"RUNNING","subSport":"GENERIC","vo2MaxValue":60.0,"fitnessAge":"20","fitnessAgeDescription":"3","analyzerMethod":5,"maxMet":17.235595703125,"maxMetCategory":"GENERIC","calibratedData":1},{"userProfilePK":96200873,"calendarDate":"2021-06-07","deviceId":3366988290,"updateTimestamp":"2021-06-14T22:37:05.0","sport":"RUNNING","subSport":"GENERIC","vo2MaxValue":60.0,"fitnessAge":"20","fitnessAgeDescription":"3","analyzerMethod":5,"maxMet":17.219207763671875,"maxMetCategory":"GENERIC","calibratedData":1},{"userProfilePK":96200873,"calendarDate":"2021-06-15","deviceId":3366988290,"updateTimestamp":"2021-06-15T22:21:23.0","sport":"RUNNING","subSport":"GENERIC","vo2MaxValue":58.0,"fitnessAge":"20","fitnessAgeDescription":"3","analyzerMethod":5,"maxMet":16.674880981445312,"maxMetCategory":"GENERIC","calibratedData":1},{"userProfilePK":96200873,"calendarDate":"2021-06-15","deviceId":3366988290,"updateTimestamp":"2021-06-16T14:58:45.0","sport":"RUNNING","subSport":"GENERIC","vo2MaxValue":59.0,"fitnessAge":"20","fitnessAgeDescription":"3","analyzerMethod":5,"maxMet":16.929733276367188,"maxMetCategory":"GENERIC","calibratedData":1},{"userProfilePK":96200873,"calendarDate":"2021-06-15","deviceId":3366988290,"updateTimestamp":"2021-06-17T22:33:12.0","sport":"RUNNING","subSport":"GENERIC","vo2MaxValue":60.0,"fitnessAge":"20","fitnessAgeDescription":"3","analyzerMethod":5,"maxMet":17.12518310546875,"maxMetCategory":"GENERIC","calibratedData":1},{"userProfilePK":96200873,"calendarDate":"2021-06-19","deviceId":3366988290,"updateTimestamp":"2021-06-19T16:44:58.0","sport":"RUNNING","subSport":"GENERIC","vo2MaxValue":60.0,"fitnessAge":"20","fitnessAgeDescription":"3","analyzerMethod":5,"maxMet":17.158218383789062,"maxMetCategory":"GENERIC","calibratedData":1},{"userProfilePK":96200873,"calendarDate":"2021-06-19","deviceId":3366988290,"updateTimestamp":"2021-06-21T22:07:38.0","sport":"RUNNING","subSport":"GENERIC","vo2MaxValue":60.0,"fitnessAge":"20","fitnessAgeDescription":"3","analyzerMethod":5,"maxMet":17.138641357421875,"maxMetCategory":"GENERIC","calibratedData":1},{"userProfilePK":96200873,"calendarDate":"2021-06-19","deviceId":3366988290,"updateTimestamp":"2021-06-22T22:28:39.0","sport":"RUNNING","subSport":"GENERIC","vo2MaxValue":61.0,"fitnessAge":"20","fitnessAgeDescription":"3","analyzerMethod":5,"maxMet":17.302536010742188,"maxMetCategory":"GENERIC","calibratedData":1},{"userProfilePK":96200873,"calendarDate":"2021-06-19","deviceId":3366988290,"updateTimestamp":"2021-06-23T15:02:48.0","sport":"RUNNING","subSport":"GENERIC","vo2MaxValue":61.0,"fitnessAge":"20","fitnessAgeDescription":"3","analyzerMethod":5,"maxMet":17.3876953125,"maxMetCategory":"GENERIC","calibratedData":1},{"userProfilePK":96200873,"calendarDate":"2021-06-19","deviceId":3366988290,"updateTimestamp":"2021-06-24T22:05:29.0","sport":"RUNNING","subSport":"GENERIC","vo2MaxValue":62.0,"fitnessAge":"20","fitnessAgeDescription":"3","analyzerMethod":5,"maxMet":17.578811645507812,"maxMetCategory":"GENERIC","calibratedData":1},{"userProfilePK":96200873,"calendarDate":"2021-06-26","deviceId":3366988290,"updateTimestamp":"2021-06-26T17:04:48.0","sport":"RUNNING","subSport":"GENERIC","vo2MaxValue":61.0,"fitnessAge":"20","fitnessAgeDescription":"3","analyzerMethod":5,"maxMet":17.546127319335938,"maxMetCategory":"GENERIC","calibratedData":1},{"userProfilePK":96200873,"calendarDate":"2021-06-26","deviceId":3366988290,"updateTimestamp":"2021-06-28T15:30:42.0","sport":"RUNNING","subSport":"GENERIC","vo2MaxValue":61.0,"fitnessAge":"20","fitnessAgeDescription":"3","analyzerMethod":5,"maxMet":17.453414916992188,"maxMetCategory":"GENERIC","calibratedData":1},{"userProfilePK":96200873,"calendarDate":"2021-06-26","deviceId":3366988290,"updateTimestamp":"2021-06-29T15:12:16.0","sport":"RUNNING","subSport":"GENERIC","vo2MaxValue":62.0,"fitnessAge":"20","fitnessAgeDescription":"3","analyzerMethod":5,"maxMet":17.712722778320312,"maxMetCategory":"GENERIC","calibratedData":1},{"userProfilePK":96200873,"calendarDate":"2021-06-26","deviceId":3366988290,"updateTimestamp":"2021-06-30T17:10:25.0","sport":"RUNNING","subSport":"GENERIC","vo2MaxValue":62.0,"fitnessAge":"20","fitnessAgeDescription":"3","analyzerMethod":5,"maxMet":17.609878540039062,"maxMetCategory":"GENERIC","calibratedData":1},{"userProfilePK":96200873,"calendarDate":"2021-06-26","deviceId":3366988290,"updateTimestamp":"2021-07-01T15:10:45.0","sport":"RUNNING","subSport":"GENERIC","vo2MaxValue":62.0,"fitnessAge":"20","fitnessAgeDescription":"3","analyzerMethod":5,"maxMet":17.851593017578125,"maxMetCategory":"GENERIC","calibratedData":1},{"userProfilePK":96200873,"calendarDate":"2021-06-26","deviceId":3366988290,"updateTimestamp":"2021-07-07T17:11:54.0","sport":"RUNNING","subSport":"GENERIC","vo2MaxValue":62.0,"fitnessAge":"20","fitnessAgeDescription":"3","analyzerMethod":5,"maxMet":17.81256103515625,"maxMetCategory":"GENERIC","calibratedData":1},{"userProfilePK":96200873,"calendarDate":"2021-06-26","deviceId":3366988290,"updateTimestamp":"2021-07-08T16:47:21.0","sport":"RUNNING","subSport":"GENERIC","vo2MaxValue":62.0,"fitnessAge":"20","fitnessAgeDescription":"3","analyzerMethod":5,"maxMet":17.798477172851562,"maxMetCategory":"GENERIC","calibratedData":1},{"userProfilePK":96200873,"calendarDate":"2021-06-26","deviceId":3366988290,"updateTimestamp":"2021-07-09T17:13:39.0","sport":"RUNNING","subSport":"GENERIC","vo2MaxValue":62.0,"fitnessAge":"20","fitnessAgeDescription":"3","analyzerMethod":5,"maxMet":17.606887817382812,"maxMetCategory":"GENERIC","calibratedData":1},{"userProfilePK":96200873,"calendarDate":"2021-06-26","deviceId":3366988290,"updateTimestamp":"2021-07-10T17:24:18.0","sport":"RUNNING","subSport":"GENERIC","vo2MaxValue":62.0,"fitnessAge":"20","fitnessAgeDescription":"3","analyzerMethod":5,"maxMet":17.6962890625,"maxMetCategory":"GENERIC","calibratedData":1},{"userProfilePK":96200873,"calendarDate":"2021-06-26","deviceId":3366988290,"updateTimestamp":"2021-07-12T17:06:04.0","sport":"RUNNING","subSport":"GENERIC","vo2MaxValue":61.0,"fitnessAge":"20","fitnessAgeDescription":"3","analyzerMethod":5,"maxMet":17.469894409179688,"maxMetCategory":"GENERIC","calibratedData":1},{"userProfilePK":96200873,"calendarDate":"2021-07-13","deviceId":3366988290,"updateTimestamp":"2021-07-13T16:35:31.0","sport":"RUNNING","subSport":"GENERIC","vo2MaxValue":63.0,"fitnessAge":"20","fitnessAgeDescription":"3","analyzerMethod":5,"maxMet":17.978988647460938,"maxMetCategory":"GENERIC","calibratedData":1},{"userProfilePK":96200873,"calendarDate":"2021-07-13","deviceId":3366988290,"updateTimestamp":"2021-07-14T17:23:58.0","sport":"RUNNING","subSport":"GENERIC","vo2MaxValue":63.0,"fitnessAge":"20","fitnessAgeDescription":"3","analyzerMethod":5,"maxMet":17.904281616210938,"maxMetCategory":"GENERIC","calibratedData":1},{"userProfilePK":96200873,"calendarDate":"2021-07-15","deviceId":3366988290,"updateTimestamp":"2021-07-15T16:35:34.0","sport":"RUNNING","subSport":"GENERIC","vo2MaxValue":63.0,"fitnessAge":"20","fitnessAgeDescription":"3","analyzerMethod":5,"maxMet":17.927047729492188,"maxMetCategory":"GENERIC","calibratedData":1},{"userProfilePK":96200873,"calendarDate":"2021-07-15","deviceId":3366988290,"updateTimestamp":"2021-07-16T17:11:36.0","sport":"RUNNING","subSport":"GENERIC","vo2MaxValue":63.0,"fitnessAge":"20","fitnessAgeDescription":"3","analyzerMethod":5,"maxMet":17.92254638671875,"maxMetCategory":"GENERIC","calibratedData":1},{"userProfilePK":96200873,"calendarDate":"2021-07-15","deviceId":3366988290,"updateTimestamp":"2021-07-17T18:02:47.0","sport":"RUNNING","subSport":"GENERIC","vo2MaxValue":63.0,"fitnessAge":"20","fitnessAgeDescription":"3","analyzerMethod":5,"maxMet":17.89617919921875,"maxMetCategory":"GENERIC","calibratedData":1},{"userProfilePK":96200873,"calendarDate":"2021-07-15","deviceId":3366988290,"updateTimestamp":"2021-07-26T23:41:29.0","sport":"RUNNING","subSport":"GENERIC","vo2MaxValue":60.0,"fitnessAge":"20","fitnessAgeDescription":"3","analyzerMethod":5,"maxMet":17.250274658203125,"maxMetCategory":"GENERIC","calibratedData":1},{"userProfilePK":96200873,"calendarDate":"2021-07-15","deviceId":3366988290,"updateTimestamp":"2021-07-27T14:10:11.0","sport":"RUNNING","subSport":"GENERIC","vo2MaxValue":60.0,"fitnessAge":"20","fitnessAgeDescription":"3","analyzerMethod":5,"maxMet":17.251983642578125,"maxMetCategory":"GENERIC","calibratedData":1},{"userProfilePK":96200873,"calendarDate":"2021-07-15","deviceId":3366988290,"updateTimestamp":"2021-07-28T17:37:06.0","sport":"RUNNING","subSport":"GENERIC","vo2MaxValue":60.0,"fitnessAge":"20","fitnessAgeDescription":"3","analyzerMethod":5,"maxMet":17.191848754882812,"maxMetCategory":"GENERIC","calibratedData":1},{"userProfilePK":96200873,"calendarDate":"2021-07-15","deviceId":3366988290,"updateTimestamp":"2021-07-29T14:09:36.0","sport":"RUNNING","subSport":"GENERIC","vo2MaxValue":60.0,"fitnessAge":"20","fitnessAgeDescription":"3","analyzerMethod":5,"maxMet":17.232513427734375,"maxMetCategory":"GENERIC","calibratedData":1},{"userProfilePK":96200873,"calendarDate":"2021-07-15","deviceId":3366988290,"updateTimestamp":"2021-07-30T16:20:30.0","sport":"RUNNING","subSport":"GENERIC","vo2MaxValue":61.0,"fitnessAge":"20","fitnessAgeDescription":"3","analyzerMethod":5,"maxMet":17.405975341796875,"maxMetCategory":"GENERIC","calibratedData":1},{"userProfilePK":96200873,"calendarDate":"2021-07-15","deviceId":3366988290,"updateTimestamp":"2021-08-01T15:46:43.0","sport":"RUNNING","subSport":"GENERIC","vo2MaxValue":62.0,"fitnessAge":"20","fitnessAgeDescription":"3","analyzerMethod":5,"maxMet":17.8323974609375,"maxMetCategory":"GENERIC","calibratedData":1},{"userProfilePK":96200873,"calendarDate":"2021-08-02","deviceId":3366988290,"updateTimestamp":"2021-08-02T17:34:22.0","sport":"RUNNING","subSport":"GENERIC","vo2MaxValue":63.0,"fitnessAge":"20","fitnessAgeDescription":"3","analyzerMethod":5,"maxMet":17.961288452148438,"maxMetCategory":"GENERIC","calibratedData":1},{"userProfilePK":96200873,"calendarDate":"2021-08-02","deviceId":3366988290,"updateTimestamp":"2021-08-03T17:01:17.0","sport":"RUNNING","subSport":"GENERIC","vo2MaxValue":63.0,"fitnessAge":"20","fitnessAgeDescription":"3","analyzerMethod":5,"maxMet":17.914199829101562,"maxMetCategory":"GENERIC","calibratedData":1},{"userProfilePK":96200873,"calendarDate":"2021-08-05","deviceId":3366988290,"updateTimestamp":"2021-08-05T17:04:33.0","sport":"RUNNING","subSport":"GENERIC","vo2MaxValue":62.0,"fitnessAge":"20","fitnessAgeDescription":"3","analyzerMethod":5,"maxMet":17.662063598632812,"maxMetCategory":"GENERIC","calibratedData":1},{"userProfilePK":96200873,"calendarDate":"2021-08-05","deviceId":3366988290,"updateTimestamp":"2021-08-06T18:25:18.0","sport":"RUNNING","subSport":"GENERIC","vo2MaxValue":61.0,"fitnessAge":"20","fitnessAgeDescription":"3","analyzerMethod":5,"maxMet":17.495697021484375,"maxMetCategory":"GENERIC","calibratedData":1},{"userProfilePK":96200873,"calendarDate":"2021-08-07","deviceId":3366988290,"updateTimestamp":"2021-08-07T15:54:24.0","sport":"RUNNING","subSport":"GENERIC","vo2MaxValue":61.0,"fitnessAge":"20","fitnessAgeDescription":"3","analyzerMethod":5,"maxMet":17.502914428710938,"maxMetCategory":"GENERIC","calibratedData":1},{"userProfilePK":96200873,"calendarDate":"2021-08-08","deviceId":3366988290,"updateTimestamp":"2021-08-09T02:58:49.0","sport":"RUNNING","subSport":"GENERIC","vo2MaxValue":61.0,"fitnessAge":"20","fitnessAgeDescription":"3","analyzerMethod":5,"maxMet":17.415145874023438,"maxMetCategory":"GENERIC","calibratedData":1},{"userProfilePK":96200873,"calendarDate":"2021-08-08","deviceId":3366988290,"updateTimestamp":"2021-08-09T17:57:14.0","sport":"RUNNING","subSport":"GENERIC","vo2MaxValue":61.0,"fitnessAge":"20","fitnessAgeDescription":"3","analyzerMethod":5,"maxMet":17.37493896484375,"maxMetCategory":"GENERIC","calibratedData":1},{"userProfilePK":96200873,"calendarDate":"2021-08-08","deviceId":3366988290,"updateTimestamp":"2021-08-10T17:52:30.0","sport":"RUNNING","subSport":"GENERIC","vo2MaxValue":61.0,"fitnessAge":"20","fitnessAgeDescription":"3","analyzerMethod":5,"maxMet":17.414581298828125,"maxMetCategory":"GENERIC","calibratedData":1},{"userProfilePK":96200873,"calendarDate":"2021-08-08","deviceId":3366988290,"updateTimestamp":"2021-08-11T18:34:09.0","sport":"RUNNING","subSport":"GENERIC","vo2MaxValue":61.0,"fitnessAge":"20","fitnessAgeDescription":"3","analyzerMethod":5,"maxMet":17.3994140625,"maxMetCategory":"GENERIC","calibratedData":1},{"userProfilePK":96200873,"calendarDate":"2021-08-08","deviceId":3366988290,"updateTimestamp":"2021-08-12T18:06:23.0","sport":"RUNNING","subSport":"GENERIC","vo2MaxValue":61.0,"fitnessAge":"20","fitnessAgeDescription":"3","analyzerMethod":5,"maxMet":17.43634033203125,"maxMetCategory":"GENERIC","calibratedData":1},{"userProfilePK":96200873,"calendarDate":"2021-08-08","deviceId":3366988290,"updateTimestamp":"2021-08-14T00:41:50.0","sport":"RUNNING","subSport":"GENERIC","vo2MaxValue":61.0,"fitnessAge":"20","fitnessAgeDescription":"3","analyzerMethod":5,"maxMet":17.416229248046875,"maxMetCategory":"GENERIC","calibratedData":1},{"userProfilePK":96200873,"calendarDate":"2021-08-08","deviceId":3366988290,"updateTimestamp":"2021-08-14T17:59:43.0","sport":"RUNNING","subSport":"GENERIC","vo2MaxValue":61.0,"fitnessAge":"20","fitnessAgeDescription":"3","analyzerMethod":5,"maxMet":17.553726196289062,"maxMetCategory":"GENERIC","calibratedData":1},{"userProfilePK":96200873,"calendarDate":"2021-08-16","deviceId":3366988290,"updateTimestamp":"2021-08-16T17:35:11.0","sport":"RUNNING","subSport":"GENERIC","vo2MaxValue":61.0,"fitnessAge":"20","fitnessAgeDescription":"3","analyzerMethod":5,"maxMet":17.48382568359375,"maxMetCategory":"GENERIC","calibratedData":1},{"userProfilePK":96200873,"calendarDate":"2021-08-17","deviceId":3366988290,"updateTimestamp":"2021-08-17T15:08:53.0","sport":"RUNNING","subSport":"GENERIC","vo2MaxValue":61.0,"fitnessAge":"20","fitnessAgeDescription":"3","analyzerMethod":5,"maxMet":17.482315063476562,"maxMetCategory":"GENERIC","calibratedData":1},{"userProfilePK":96200873,"calendarDate":"2021-08-18","deviceId":3366988290,"updateTimestamp":"2021-08-18T17:15:29.0","sport":"RUNNING","subSport":"GENERIC","vo2MaxValue":61.0,"fitnessAge":"20","fitnessAgeDescription":"3","analyzerMethod":5,"maxMet":17.520599365234375,"maxMetCategory":"GENERIC","calibratedData":1},{"userProfilePK":96200873,"calendarDate":"2021-08-19","deviceId":3366988290,"updateTimestamp":"2021-08-19T17:36:03.0","sport":"RUNNING","subSport":"GENERIC","vo2MaxValue":61.0,"fitnessAge":"20","fitnessAgeDescription":"3","analyzerMethod":5,"maxMet":17.529525756835938,"maxMetCategory":"GENERIC","calibratedData":1},{"userProfilePK":96200873,"calendarDate":"2021-08-20","deviceId":3366988290,"updateTimestamp":"2021-08-20T17:38:29.0","sport":"RUNNING","subSport":"GENERIC","vo2MaxValue":61.0,"fitnessAge":"20","fitnessAgeDescription":"3","analyzerMethod":5,"maxMet":17.500198364257812,"maxMetCategory":"GENERIC","calibratedData":1},{"userProfilePK":96200873,"calendarDate":"2021-08-20","deviceId":3366988290,"updateTimestamp":"2021-08-21T17:07:46.0","sport":"RUNNING","subSport":"GENERIC","vo2MaxValue":61.0,"fitnessAge":"20","fitnessAgeDescription":"3","analyzerMethod":5,"maxMet":17.545730590820312,"maxMetCategory":"GENERIC","calibratedData":1},{"userProfilePK":96200873,"calendarDate":"2021-08-23","deviceId":3366988290,"updateTimestamp":"2021-08-23T18:05:06.0","sport":"RUNNING","subSport":"GENERIC","vo2MaxValue":62.0,"fitnessAge":"20","fitnessAgeDescription":"3","analyzerMethod":5,"maxMet":17.702194213867188,"maxMetCategory":"GENERIC","calibratedData":1},{"userProfilePK":96200873,"calendarDate":"2021-08-23","deviceId":3366988290,"updateTimestamp":"2021-08-24T17:36:15.0","sport":"RUNNING","subSport":"GENERIC","vo2MaxValue":62.0,"fitnessAge":"20","fitnessAgeDescription":"3","analyzerMethod":5,"maxMet":17.800872802734375,"maxMetCategory":"GENERIC","calibratedData":1},{"userProfilePK":96200873,"calendarDate":"2021-08-23","deviceId":3366988290,"updateTimestamp":"2021-08-25T18:02:25.0","sport":"RUNNING","subSport":"GENERIC","vo2MaxValue":62.0,"fitnessAge":"20","fitnessAgeDescription":"3","analyzerMethod":5,"maxMet":17.655548095703125,"maxMetCategory":"GENERIC","calibratedData":1},{"userProfilePK":96200873,"calendarDate":"2021-08-26","deviceId":3366988290,"updateTimestamp":"2021-08-26T17:09:39.0","sport":"RUNNING","subSport":"GENERIC","vo2MaxValue":62.0,"fitnessAge":"20","fitnessAgeDescription":"3","analyzerMethod":5,"maxMet":17.660247802734375,"maxMetCategory":"GENERIC","calibratedData":1},{"userProfilePK":96200873,"calendarDate":"2021-08-28","deviceId":3366988290,"updateTimestamp":"2021-08-28T17:19:02.0","sport":"RUNNING","subSport":"GENERIC","vo2MaxValue":62.0,"fitnessAge":"20","fitnessAgeDescription":"3","analyzerMethod":5,"maxMet":17.651840209960938,"maxMetCategory":"GENERIC","calibratedData":1},{"userProfilePK":96200873,"calendarDate":"2021-08-28","deviceId":3366988290,"updateTimestamp":"2021-08-31T23:26:37.0","sport":"RUNNING","subSport":"GENERIC","vo2MaxValue":62.0,"fitnessAge":"20","fitnessAgeDescription":"3","analyzerMethod":5,"maxMet":17.7515869140625,"maxMetCategory":"GENERIC","calibratedData":1},{"userProfilePK":96200873,"calendarDate":"2021-08-28","deviceId":3366988290,"updateTimestamp":"2021-09-02T23:16:24.0","sport":"RUNNING","subSport":"GENERIC","vo2MaxValue":62.0,"fitnessAge":"20","fitnessAgeDescription":"3","analyzerMethod":5,"maxMet":17.62408447265625,"maxMetCategory":"GENERIC","calibratedData":1},{"userProfilePK":96200873,"calendarDate":"2021-08-28","deviceId":3366988290,"updateTimestamp":"2021-09-04T16:43:07.0","sport":"RUNNING","subSport":"GENERIC","vo2MaxValue":62.0,"fitnessAge":"20","fitnessAgeDescription":"3","analyzerMethod":5,"maxMet":17.583023071289062,"maxMetCategory":"GENERIC","calibratedData":1},{"userProfilePK":96200873,"calendarDate":"2021-09-07","deviceId":3366988290,"updateTimestamp":"2021-09-07T23:33:13.0","sport":"RUNNING","subSport":"GENERIC","vo2MaxValue":61.0,"fitnessAge":"20","fitnessAgeDescription":"3","analyzerMethod":5,"maxMet":17.545074462890625,"maxMetCategory":"GENERIC","calibratedData":1},{"userProfilePK":96200873,"calendarDate":"2021-09-07","deviceId":3366988290,"updateTimestamp":"2021-09-09T23:25:54.0","sport":"RUNNING","subSport":"GENERIC","vo2MaxValue":61.0,"fitnessAge":"20","fitnessAgeDescription":"3","analyzerMethod":5,"maxMet":17.436187744140625,"maxMetCategory":"GENERIC","calibratedData":1},{"userProfilePK":96200873,"calendarDate":"2021-09-07","deviceId":3366988290,"updateTimestamp":"2021-09-12T03:25:23.0","sport":"RUNNING","subSport":"GENERIC","vo2MaxValue":62.0,"fitnessAge":"20","fitnessAgeDescription":"3","analyzerMethod":5,"maxMet":17.6939697265625,"maxMetCategory":"GENERIC","calibratedData":1},{"userProfilePK":96200873,"calendarDate":"2021-09-07","deviceId":3366988290,"updateTimestamp":"2021-09-15T23:19:58.0","sport":"RUNNING","subSport":"GENERIC","vo2MaxValue":62.0,"fitnessAge":"20","fitnessAgeDescription":"3","analyzerMethod":5,"maxMet":17.843856811523438,"maxMetCategory":"GENERIC","calibratedData":1},{"userProfilePK":96200873,"calendarDate":"2021-09-07","deviceId":3366988290,"updateTimestamp":"2021-09-18T17:17:37.0","sport":"RUNNING","subSport":"GENERIC","vo2MaxValue":62.0,"fitnessAge":"20","fitnessAgeDescription":"3","analyzerMethod":5,"maxMet":17.594268798828125,"maxMetCategory":"GENERIC","calibratedData":1},{"userProfilePK":96200873,"calendarDate":"2021-09-07","deviceId":3366988290,"updateTimestamp":"2021-09-23T23:30:45.0","sport":"RUNNING","subSport":"GENERIC","vo2MaxValue":61.0,"fitnessAge":"20","fitnessAgeDescription":"3","analyzerMethod":5,"maxMet":17.35870361328125,"maxMetCategory":"GENERIC","calibratedData":1},{"userProfilePK":96200873,"calendarDate":"2021-09-07","deviceId":3366988290,"updateTimestamp":"2021-09-25T21:51:40.0","sport":"RUNNING","subSport":"GENERIC","vo2MaxValue":61.0,"fitnessAge":"20","fitnessAgeDescription":"3","analyzerMethod":5,"maxMet":17.452606201171875,"maxMetCategory":"GENERIC","calibratedData":1},{"userProfilePK":96200873,"calendarDate":"2021-09-07","deviceId":3366988290,"updateTimestamp":"2021-09-28T23:22:20.0","sport":"RUNNING","subSport":"GENERIC","vo2MaxValue":61.0,"fitnessAge":"20","fitnessAgeDescription":"3","analyzerMethod":5,"maxMet":17.470291137695312,"maxMetCategory":"GENERIC","calibratedData":1},{"userProfilePK":96200873,"calendarDate":"2021-09-07","deviceId":3366988290,"updateTimestamp":"2021-09-30T23:16:24.0","sport":"RUNNING","subSport":"GENERIC","vo2MaxValue":61.0,"fitnessAge":"20","fitnessAgeDescription":"3","analyzerMethod":5,"maxMet":17.4176025390625,"maxMetCategory":"GENERIC","calibratedData":1},{"userProfilePK":96200873,"calendarDate":"2021-09-07","deviceId":3366988290,"updateTimestamp":"2021-10-02T18:00:23.0","sport":"RUNNING","subSport":"GENERIC","vo2MaxValue":61.0,"fitnessAge":"20","fitnessAgeDescription":"3","analyzerMethod":5,"maxMet":17.336456298828125,"maxMetCategory":"GENERIC","calibratedData":1},{"userProfilePK":96200873,"calendarDate":"2021-09-07","deviceId":3366988290,"updateTimestamp":"2021-10-07T00:39:44.0","sport":"RUNNING","subSport":"GENERIC","vo2MaxValue":62.0,"fitnessAge":"20","fitnessAgeDescription":"3","analyzerMethod":5,"maxMet":17.763565063476562,"maxMetCategory":"GENERIC","calibratedData":1},{"userProfilePK":96200873,"calendarDate":"2021-09-07","deviceId":3366988290,"updateTimestamp":"2021-10-07T23:15:18.0","sport":"RUNNING","subSport":"GENERIC","vo2MaxValue":61.0,"fitnessAge":"20","fitnessAgeDescription":"3","analyzerMethod":5,"maxMet":17.491714477539062,"maxMetCategory":"GENERIC","calibratedData":1},{"userProfilePK":96200873,"calendarDate":"2021-09-07","deviceId":3366988290,"updateTimestamp":"2021-10-09T19:48:50.0","sport":"RUNNING","subSport":"GENERIC","vo2MaxValue":63.0,"fitnessAge":"20","fitnessAgeDescription":"3","analyzerMethod":5,"maxMet":18.059738159179688,"maxMetCategory":"GENERIC","calibratedData":1},{"userProfilePK":96200873,"calendarDate":"2021-09-07","deviceId":3366988290,"updateTimestamp":"2021-10-13T23:24:32.0","sport":"RUNNING","subSport":"GENERIC","vo2MaxValue":64.0,"fitnessAge":"20","fitnessAgeDescription":"3","analyzerMethod":5,"maxMet":18.420150756835938,"maxMetCategory":"GENERIC","calibratedData":1},{"userProfilePK":96200873,"calendarDate":"2021-09-07","deviceId":3366988290,"updateTimestamp":"2021-10-14T23:16:28.0","sport":"RUNNING","subSport":"GENERIC","vo2MaxValue":64.0,"fitnessAge":"20","fitnessAgeDescription":"3","analyzerMethod":5,"maxMet":18.334625244140625,"maxMetCategory":"GENERIC","calibratedData":1},{"userProfilePK":96200873,"calendarDate":"2021-09-07","deviceId":3366988290,"updateTimestamp":"2021-10-19T23:06:05.0","sport":"RUNNING","subSport":"GENERIC","vo2MaxValue":64.0,"fitnessAge":"20","fitnessAgeDescription":"3","analyzerMethod":5,"maxMet":18.183334350585938,"maxMetCategory":"GENERIC","calibratedData":1},{"userProfilePK":96200873,"calendarDate":"2021-09-07","deviceId":3366988290,"updateTimestamp":"2021-10-21T23:02:43.0","sport":"RUNNING","subSport":"GENERIC","vo2MaxValue":63.0,"fitnessAge":"20","fitnessAgeDescription":"3","analyzerMethod":5,"maxMet":17.859848022460938,"maxMetCategory":"GENERIC","calibratedData":1},{"userProfilePK":96200873,"calendarDate":"2021-09-07","deviceId":3366988290,"updateTimestamp":"2021-10-23T22:39:25.0","sport":"RUNNING","subSport":"GENERIC","vo2MaxValue":64.0,"fitnessAge":"20","fitnessAgeDescription":"3","analyzerMethod":5,"maxMet":18.300537109375,"maxMetCategory":"GENERIC","calibratedData":1},{"userProfilePK":96200873,"calendarDate":"2021-09-07","deviceId":3366988290,"updateTimestamp":"2021-10-26T22:57:27.0","sport":"RUNNING","subSport":"GENERIC","vo2MaxValue":64.0,"fitnessAge":"20","fitnessAgeDescription":"3","analyzerMethod":5,"maxMet":18.1488037109375,"maxMetCategory":"GENERIC","calibratedData":1},{"userProfilePK":96200873,"calendarDate":"2021-09-07","deviceId":3366988290,"updateTimestamp":"2021-10-28T22:53:41.0","sport":"RUNNING","subSport":"GENERIC","vo2MaxValue":63.0,"fitnessAge":"20","fitnessAgeDescription":"3","analyzerMethod":5,"maxMet":18.041122436523438,"maxMetCategory":"GENERIC","calibratedData":1}]